TrafficLight.v
module traffic_light_4road (
    input clk,
    input reset,
    output reg red1, output reg yellow1, output reg green1,
    output reg red2, output reg yellow2, output reg green2,
    output reg red3, output reg yellow3, output reg green3,
    output reg red4, output reg yellow4, output reg green4
);
    // State encoding (3 bits)
    localparam S1_GREEN  = 3'd0;
    localparam S1_YELLOW = 3'd1;
    localparam S2_GREEN  = 3'd2;
    localparam S2_YELLOW = 3'd3;
    localparam S3_GREEN  = 3'd4;
    localparam S3_YELLOW = 3'd5;
    localparam S4_GREEN  = 3'd6;
    localparam S4_YELLOW = 3'd7;

    reg [2:0] state, next_state;

    // State register with asynchronous reset to Road1-green
    always @(posedge clk or posedge reset) begin
        if (reset)
            state <= S1_GREEN;
        else
            state <= next_state;
    end

    // Next-state and output logic
    always @(*) begin
        // Default: all roads RED=1, green/yellow=0
        red1 = 1; yellow1 = 0; green1 = 0;
        red2 = 1; yellow2 = 0; green2 = 0;
        red3 = 1; yellow3 = 0; green3 = 0;
        red4 = 1; yellow4 = 0; green4 = 0;
        next_state = state;  // default stay

        case (state)
            S1_GREEN: begin
                red1 = 0; green1 = 1; yellow1 = 0;
                next_state = S1_YELLOW;
            end
            S1_YELLOW: begin
                red1 = 0; green1 = 0; yellow1 = 1;
                next_state = S2_GREEN;
            end
            S2_GREEN: begin
                red2 = 0; green2 = 1; yellow2 = 0;
                next_state = S2_YELLOW;
            end
            S2_YELLOW: begin
                red2 = 0; green2 = 0; yellow2 = 1;
                next_state = S3_GREEN;
            end
            S3_GREEN: begin
                red3 = 0; green3 = 1; yellow3 = 0;
                next_state = S3_YELLOW;
            end
            S3_YELLOW: begin
                red3 = 0; green3 = 0; yellow3 = 1;
                next_state = S4_GREEN;
            end
            S4_GREEN: begin
                red4 = 0; green4 = 1; yellow4 = 0;
                next_state = S4_YELLOW;
            end
            S4_YELLOW: begin
                red4 = 0; green4 = 0; yellow4 = 1;
                next_state = S1_GREEN;
            end
            default: begin
                // Should not occur; reset to safe state
                next_state = S1_GREEN;
            end
        endcase
    end
endmodule

TrafficLight_tb.v
`timescale 1ns/1ps
module TrafficLight_tb;
  reg clk;
  reg reset;
  wire red1, yellow1, green1;
  wire red2, yellow2, green2;
  wire red3, yellow3, green3;
  wire red4, yellow4, green4;

  // Instantiate the traffic light controller module
  traffic_light_4road dut (
    .clk(clk),
    .reset(reset),
    .red1(red1), .yellow1(yellow1), .green1(green1),
    .red2(red2), .yellow2(yellow2), .green2(green2),
    .red3(red3), .yellow3(yellow3), .green3(green3),
    .red4(red4), .yellow4(yellow4), .green4(green4)
  );

  initial begin
    // Dump waveform to a file for GTKWave
    $dumpfile("traffic_light.vcd");
    $dumpvars(0, TrafficLight_tb);
    // Run long enough to see two full cycles of 8 states (8 states * 10ns each = 80ns; here we use 200ns)
    #200 $finish;
  end

  initial begin
    // Initialize clock and assert reset briefly
    clk = 0;
    reset = 1;
    #10 reset = 0;
  end

  // 10 ns clock period: toggle every 5ns
  always #5 clk = ~clk;
endmodule

traffic_light.vcd
$date
	Wed Jul 30 20:26:59 2025
$end
$version
	Icarus Verilog
$end
$timescale
	1ps
$end
$scope module TrafficLight_tb $end
$var wire 1 ! yellow4 $end
$var wire 1 " yellow3 $end
$var wire 1 # yellow2 $end
$var wire 1 $ yellow1 $end
$var wire 1 % red4 $end
$var wire 1 & red3 $end
$var wire 1 ' red2 $end
$var wire 1 ( red1 $end
$var wire 1 ) green4 $end
$var wire 1 * green3 $end
$var wire 1 + green2 $end
$var wire 1 , green1 $end
$var reg 1 - clk $end
$var reg 1 . reset $end
$scope module dut $end
$var wire 1 - clk $end
$var wire 1 . reset $end
$var parameter 3 / S1_GREEN $end
$var parameter 3 0 S1_YELLOW $end
$var parameter 3 1 S2_GREEN $end
$var parameter 3 2 S2_YELLOW $end
$var parameter 3 3 S3_GREEN $end
$var parameter 3 4 S3_YELLOW $end
$var parameter 3 5 S4_GREEN $end
$var parameter 3 6 S4_YELLOW $end
$var reg 1 , green1 $end
$var reg 1 + green2 $end
$var reg 1 * green3 $end
$var reg 1 ) green4 $end
$var reg 3 7 next_state [2:0] $end
$var reg 1 ( red1 $end
$var reg 1 ' red2 $end
$var reg 1 & red3 $end
$var reg 1 % red4 $end
$var reg 3 8 state [2:0] $end
$var reg 1 $ yellow1 $end
$var reg 1 # yellow2 $end
$var reg 1 " yellow3 $end
$var reg 1 ! yellow4 $end
$upscope $end
$upscope $end
$enddefinitions $end
$comment Show the parameter values. $end
$dumpall
b111 6
b110 5
b101 4
b100 3
b11 2
b10 1
b1 0
b0 /
$end
#0
$dumpvars
b0 8
b1 7
1.
0-
1,
0+
0*
0)
0(
1'
1&
1%
0$
0#
0"
0!
$end
#5000
1-
#10000
0-
0.
#15000
b10 7
1$
0,
0(
b1 8
1-
#20000
0-
#25000
b11 7
1+
0'
0$
1(
b10 8
1-
#30000
0-
#35000
b100 7
1#
0+
0'
b11 8
1-
#40000
0-
#45000
b101 7
1*
0&
0#
1'
b100 8
1-
#50000
0-
#55000
b110 7
1"
0*
0&
b101 8
1-
#60000
0-
#65000
b111 7
1)
0%
0"
1&
b110 8
1-
#70000
0-
#75000
b0 7
1!
0)
0%
b111 8
1-
#80000
0-
#85000
b1 7
1,
0(
0!
1%
b0 8
1-
#90000
0-
#95000
b10 7
1$
0,
0(
b1 8
1-
#100000
0-
#105000
b11 7
1+
0'
0$
1(
b10 8
1-
#110000
0-
#115000
b100 7
1#
0+
0'
b11 8
1-
#120000
0-
#125000
b101 7
1*
0&
0#
1'
b100 8
1-
#130000
0-
#135000
b110 7
1"
0*
0&
b101 8
1-
#140000
0-
#145000
b111 7
1)
0%
0"
1&
b110 8
1-
#150000
0-
#155000
b0 7
1!
0)
0%
b111 8
1-
#160000
0-
#165000
b1 7
1,
0(
0!
1%
b0 8
1-
#170000
0-
#175000
b10 7
1$
0,
0(
b1 8
1-
#180000
0-
#185000
b11 7
1+
0'
0$
1(
b10 8
1-
#190000
0-
#195000
b100 7
1#
0+
0'
b11 8
1-
