traffic_lights.v
// traffic_lights.v
module traffic_lights(
    input  wire clk,
    input  wire reset,
    // Road 1 → {2,3,4}
    output reg R1_L_red, R1_L_yellow, R1_L_green,
    output reg R1_S_red, R1_S_yellow, R1_S_green,
    output reg R1_R_red, R1_R_yellow, R1_R_green,
    // Road 2
    output reg R2_L_red, R2_L_yellow, R2_L_green,
    output reg R2_S_red, R2_S_yellow, R2_S_green,
    output reg R2_R_red, R2_R_yellow, R2_R_green,
    // Road 3
    output reg R3_L_red, R3_L_yellow, R3_L_green,
    output reg R3_S_red, R3_S_yellow, R3_S_green,
    output reg R3_R_red, R3_R_yellow, R3_R_green,
    // Road 4
    output reg R4_L_red, R4_L_yellow, R4_L_green,
    output reg R4_S_red, R4_S_yellow, R4_S_green,
    output reg R4_R_red, R4_R_yellow, R4_R_green
);

    // Phase definitions: green, yellow, buffer for 4 main groups
    localparam PH1_G = 0, PH1_Y = 1, BUF1 = 2,
               PH2_G = 3, PH2_Y = 4, BUF2 = 5,
               PH3_G = 6, PH3_Y = 7, BUF3 = 8,
               PH4_G = 9, PH4_Y = 10, BUF4 = 11;

    reg [3:0] state;
    reg [7:0] cnt, limit;

    // Timing parameters
    localparam T_GREEN  = 30;
    localparam T_YELLOW = 5;
    localparam T_BUF    = 5;

    // FSM sequential logic
    always @(posedge clk or posedge reset) begin
        if (reset) begin
            state <= PH1_G;
            cnt   <= 0;
        end else begin
            // choose duration
            if (state % 3 == 0)       limit = T_GREEN;  // G phases
            else if (state % 3 == 1)  limit = T_YELLOW; // Y phases
            else                       limit = T_BUF;    // Buffer

            if (cnt < limit - 1)
                cnt <= cnt + 1;
            else begin
                cnt <= 0;
                state <= (state == BUF4) ? PH1_G : state + 1;
            end
        end
    end

    // Output logic: default red, then override
    always @(*) begin
        // default all red
        {R1_L_red,R1_S_red,R1_R_red,
         R2_L_red,R2_S_red,R2_R_red,
         R3_L_red,R3_S_red,R3_R_red,
         R4_L_red,R4_S_red,R4_R_red} = {12{1'b1}};
        {R1_L_yellow,R1_S_yellow,R1_R_yellow,
         R2_L_yellow,R2_S_yellow,R2_R_yellow,
         R3_L_yellow,R3_S_yellow,R3_R_yellow,
         R4_L_yellow,R4_S_yellow,R4_R_yellow} = {12{1'b0}};
        {R1_L_green,R1_S_green,R1_R_green,
         R2_L_green,R2_S_green,R2_R_green,
         R3_L_green,R3_S_green,R3_R_green,
         R4_L_green,R4_S_green,R4_R_green} = {12{1'b0}};

        case(state)
            // Phase 1: R1_S, R1_L, R3_S, R3_L green/yellow
            PH1_G: begin R1_S_green=1; R1_S_red=0;
                     R1_L_green=1; R1_L_red=0;
                     R3_S_green=1; R3_S_red=0;
                     R3_L_green=1; R3_L_red=0; end
            PH1_Y: begin R1_S_yellow=1; R1_S_red=0;
                     R1_L_yellow=1; R1_L_red=0;
                     R3_S_yellow=1; R3_S_red=0;
                     R3_L_yellow=1; R3_L_red=0; end

            // Phase 2: R1_R, R2_R
            PH2_G: begin R1_R_green=1; R1_R_red=0;
                     R2_R_green=1; R2_R_red=0; end
            PH2_Y: begin R1_R_yellow=1; R1_R_red=0;
                     R2_R_yellow=1; R2_R_red=0; end

            // Phase 3: R2_S, R2_L, R4_S, R4_L
            PH3_G: begin R2_S_green=1; R2_S_red=0;
                     R2_L_green=1; R2_L_red=0;
                     R4_S_green=1; R4_S_red=0;
                     R4_L_green=1; R4_L_red=0; end
            PH3_Y: begin R2_S_yellow=1; R2_S_red=0;
                     R2_L_yellow=1; R2_L_red=0;
                     R4_S_yellow=1; R4_S_red=0;
                     R4_L_yellow=1; R4_L_red=0; end

            // Phase 4: R3_R, R4_R
            PH4_G: begin R3_R_green=1; R3_R_red=0;
                     R4_R_green=1; R4_R_red=0; end
            PH4_Y: begin R3_R_yellow=1; R3_R_red=0;
                     R4_R_yellow=1; R4_R_red=0; end
            default: ;
        endcase
    end
endmodule

tb_traffic.v
// tb_traffic.v
`timescale 1ns/1ps
module tb_traffic;
    reg clk = 0;
    reg reset;
    // Wires for movement signals
    wire R1_L_red, R1_L_yellow, R1_L_green;
    wire R1_S_red, R1_S_yellow, R1_S_green;
    wire R1_R_red, R1_R_yellow, R1_R_green;
    wire R2_L_red, R2_L_yellow, R2_L_green;
    wire R2_S_red, R2_S_yellow, R2_S_green;
    wire R2_R_red, R2_R_yellow, R2_R_green;
    wire R3_L_red, R3_L_yellow, R3_L_green;
    wire R3_S_red, R3_S_yellow, R3_S_green;
    wire R3_R_red, R3_R_yellow, R3_R_green;
    wire R4_L_red, R4_L_yellow, R4_L_green;
    wire R4_S_red, R4_S_yellow, R4_S_green;
    wire R4_R_red, R4_R_yellow, R4_R_green;

    // Instantiate DUT
    traffic_lights uut (
        .clk(clk), .reset(reset),
        .R1_L_red(R1_L_red), .R1_L_yellow(R1_L_yellow), .R1_L_green(R1_L_green),
        .R1_S_red(R1_S_red), .R1_S_yellow(R1_S_yellow), .R1_S_green(R1_S_green),
        .R1_R_red(R1_R_red), .R1_R_yellow(R1_R_yellow), .R1_R_green(R1_R_green),
        .R2_L_red(R2_L_red), .R2_L_yellow(R2_L_yellow), .R2_L_green(R2_L_green),
        .R2_S_red(R2_S_red), .R2_S_yellow(R2_S_yellow), .R2_S_green(R2_S_green),
        .R2_R_red(R2_R_red), .R2_R_yellow(R2_R_yellow), .R2_R_green(R2_R_green),
        .R3_L_red(R3_L_red), .R3_L_yellow(R3_L_yellow), .R3_L_green(R3_L_green),
        .R3_S_red(R3_S_red), .R3_S_yellow(R3_S_yellow), .R3_S_green(R3_S_green),
        .R3_R_red(R3_R_red), .R3_R_yellow(R3_R_yellow), .R3_R_green(R3_R_green),
        .R4_L_red(R4_L_red), .R4_L_yellow(R4_L_yellow), .R4_L_green(R4_L_green),
        .R4_S_red(R4_S_red), .R4_S_yellow(R4_S_yellow), .R4_S_green(R4_S_green),
        .R4_R_red(R4_R_red), .R4_R_yellow(R4_R_yellow), .R4_R_green(R4_R_green)
    );

    // Clock generation
    always #5 clk = ~clk;

    initial begin
        // Waveform dump
        $dumpfile("traffic_lights.vcd");
        $dumpvars(0, tb_traffic);

        // Reset pulse
        reset = 1; #10;
        reset = 0;

        // Simulate for 1000 ns
        #1000 $finish;
    end
endmodule

traffic_lights.vcd
$date
	Thu Jul 31 10:47:35 2025
$end
$version
	Icarus Verilog
$end
$timescale
	1ps
$end
$scope module tb_traffic $end
$var wire 1 ! R4_S_yellow $end
$var wire 1 " R4_S_red $end
$var wire 1 # R4_S_green $end
$var wire 1 $ R4_R_yellow $end
$var wire 1 % R4_R_red $end
$var wire 1 & R4_R_green $end
$var wire 1 ' R4_L_yellow $end
$var wire 1 ( R4_L_red $end
$var wire 1 ) R4_L_green $end
$var wire 1 * R3_S_yellow $end
$var wire 1 + R3_S_red $end
$var wire 1 , R3_S_green $end
$var wire 1 - R3_R_yellow $end
$var wire 1 . R3_R_red $end
$var wire 1 / R3_R_green $end
$var wire 1 0 R3_L_yellow $end
$var wire 1 1 R3_L_red $end
$var wire 1 2 R3_L_green $end
$var wire 1 3 R2_S_yellow $end
$var wire 1 4 R2_S_red $end
$var wire 1 5 R2_S_green $end
$var wire 1 6 R2_R_yellow $end
$var wire 1 7 R2_R_red $end
$var wire 1 8 R2_R_green $end
$var wire 1 9 R2_L_yellow $end
$var wire 1 : R2_L_red $end
$var wire 1 ; R2_L_green $end
$var wire 1 < R1_S_yellow $end
$var wire 1 = R1_S_red $end
$var wire 1 > R1_S_green $end
$var wire 1 ? R1_R_yellow $end
$var wire 1 @ R1_R_red $end
$var wire 1 A R1_R_green $end
$var wire 1 B R1_L_yellow $end
$var wire 1 C R1_L_red $end
$var wire 1 D R1_L_green $end
$var reg 1 E clk $end
$var reg 1 F reset $end
$scope module uut $end
$var wire 1 E clk $end
$var wire 1 F reset $end
$var parameter 32 G BUF1 $end
$var parameter 32 H BUF2 $end
$var parameter 32 I BUF3 $end
$var parameter 32 J BUF4 $end
$var parameter 32 K PH1_G $end
$var parameter 32 L PH1_Y $end
$var parameter 32 M PH2_G $end
$var parameter 32 N PH2_Y $end
$var parameter 32 O PH3_G $end
$var parameter 32 P PH3_Y $end
$var parameter 32 Q PH4_G $end
$var parameter 32 R PH4_Y $end
$var parameter 32 S T_BUF $end
$var parameter 32 T T_GREEN $end
$var parameter 32 U T_YELLOW $end
$var reg 1 D R1_L_green $end
$var reg 1 C R1_L_red $end
$var reg 1 B R1_L_yellow $end
$var reg 1 A R1_R_green $end
$var reg 1 @ R1_R_red $end
$var reg 1 ? R1_R_yellow $end
$var reg 1 > R1_S_green $end
$var reg 1 = R1_S_red $end
$var reg 1 < R1_S_yellow $end
$var reg 1 ; R2_L_green $end
$var reg 1 : R2_L_red $end
$var reg 1 9 R2_L_yellow $end
$var reg 1 8 R2_R_green $end
$var reg 1 7 R2_R_red $end
$var reg 1 6 R2_R_yellow $end
$var reg 1 5 R2_S_green $end
$var reg 1 4 R2_S_red $end
$var reg 1 3 R2_S_yellow $end
$var reg 1 2 R3_L_green $end
$var reg 1 1 R3_L_red $end
$var reg 1 0 R3_L_yellow $end
$var reg 1 / R3_R_green $end
$var reg 1 . R3_R_red $end
$var reg 1 - R3_R_yellow $end
$var reg 1 , R3_S_green $end
$var reg 1 + R3_S_red $end
$var reg 1 * R3_S_yellow $end
$var reg 1 ) R4_L_green $end
$var reg 1 ( R4_L_red $end
$var reg 1 ' R4_L_yellow $end
$var reg 1 & R4_R_green $end
$var reg 1 % R4_R_red $end
$var reg 1 $ R4_R_yellow $end
$var reg 1 # R4_S_green $end
$var reg 1 " R4_S_red $end
$var reg 1 ! R4_S_yellow $end
$var reg 8 V cnt [7:0] $end
$var reg 8 W limit [7:0] $end
$var reg 4 X state [3:0] $end
$upscope $end
$upscope $end
$enddefinitions $end
$comment Show the parameter values. $end
$dumpall
b101 U
b11110 T
b101 S
b1010 R
b1001 Q
b111 P
b110 O
b100 N
b11 M
b1 L
b0 K
b1011 J
b1000 I
b101 H
b10 G
$end
#0
$dumpvars
b0 X
bx W
b0 V
1F
0E
1D
0C
0B
0A
1@
0?
1>
0=
0<
0;
1:
09
08
17
06
05
14
03
12
01
00
0/
1.
0-
1,
0+
0*
0)
1(
0'
0&
1%
0$
0#
1"
0!
$end
#5000
1E
#10000
0E
0F
#15000
b1 V
b11110 W
1E
#20000
0E
#25000
b10 V
1E
#30000
0E
#35000
b11 V
1E
#40000
0E
#45000
b100 V
1E
#50000
0E
#55000
b101 V
1E
#60000
0E
#65000
b110 V
1E
#70000
0E
#75000
b111 V
1E
#80000
0E
#85000
b1000 V
1E
#90000
0E
#95000
b1001 V
1E
#100000
0E
#105000
b1010 V
1E
#110000
0E
#115000
b1011 V
1E
#120000
0E
#125000
b1100 V
1E
#130000
0E
#135000
b1101 V
1E
#140000
0E
#145000
b1110 V
1E
#150000
0E
#155000
b1111 V
1E
#160000
0E
#165000
b10000 V
1E
#170000
0E
#175000
b10001 V
1E
#180000
0E
#185000
b10010 V
1E
#190000
0E
#195000
b10011 V
1E
#200000
0E
#205000
b10100 V
1E
#210000
0E
#215000
b10101 V
1E
#220000
0E
#225000
b10110 V
1E
#230000
0E
#235000
b10111 V
1E
#240000
0E
#245000
b11000 V
1E
#250000
0E
#255000
b11001 V
1E
#260000
0E
#265000
b11010 V
1E
#270000
0E
#275000
b11011 V
1E
#280000
0E
#285000
b11100 V
1E
#290000
0E
#295000
b11101 V
1E
#300000
0E
#305000
10
1*
1B
1<
0D
0>
02
0,
0C
0=
01
0+
b1 X
b0 V
1E
#310000
0E
#315000
b1 V
b101 W
1E
#320000
0E
#325000
b10 V
1E
#330000
0E
#335000
b11 V
1E
#340000
0E
#345000
b100 V
1E
#350000
0E
#355000
0B
0<
00
0*
1C
1=
11
1+
b10 X
b0 V
1E
#360000
0E
#365000
b1 V
1E
#370000
0E
#375000
b10 V
1E
#380000
0E
#385000
b11 V
1E
#390000
0E
#395000
b100 V
1E
#400000
0E
#405000
07
18
0@
1A
b11 X
b0 V
1E
#410000
0E
#415000
b1 V
b11110 W
1E
#420000
0E
#425000
b10 V
1E
#430000
0E
#435000
b11 V
1E
#440000
0E
#445000
b100 V
1E
#450000
0E
#455000
b101 V
1E
#460000
0E
#465000
b110 V
1E
#470000
0E
#475000
b111 V
1E
#480000
0E
#485000
b1000 V
1E
#490000
0E
#495000
b1001 V
1E
#500000
0E
#505000
b1010 V
1E
#510000
0E
#515000
b1011 V
1E
#520000
0E
#525000
b1100 V
1E
#530000
0E
#535000
b1101 V
1E
#540000
0E
#545000
b1110 V
1E
#550000
0E
#555000
b1111 V
1E
#560000
0E
#565000
b10000 V
1E
#570000
0E
#575000
b10001 V
1E
#580000
0E
#585000
b10010 V
1E
#590000
0E
#595000
b10011 V
1E
#600000
0E
#605000
b10100 V
1E
#610000
0E
#615000
b10101 V
1E
#620000
0E
#625000
b10110 V
1E
#630000
0E
#635000
b10111 V
1E
#640000
0E
#645000
b11000 V
1E
#650000
0E
#655000
b11001 V
1E
#660000
0E
#665000
b11010 V
1E
#670000
0E
#675000
b11011 V
1E
#680000
0E
#685000
b11100 V
1E
#690000
0E
#695000
b11101 V
1E
#700000
0E
#705000
16
1?
0A
08
0@
07
b100 X
b0 V
1E
#710000
0E
#715000
b1 V
b101 W
1E
#720000
0E
#725000
b10 V
1E
#730000
0E
#735000
b11 V
1E
#740000
0E
#745000
b100 V
1E
#750000
0E
#755000
0?
06
1@
17
b101 X
b0 V
1E
#760000
0E
#765000
b1 V
1E
#770000
0E
#775000
b10 V
1E
#780000
0E
#785000
b11 V
1E
#790000
0E
#795000
b100 V
1E
#800000
0E
#805000
0(
1)
0"
1#
0:
1;
04
15
b110 X
b0 V
1E
#810000
0E
#815000
b1 V
b11110 W
1E
#820000
0E
#825000
b10 V
1E
#830000
0E
#835000
b11 V
1E
#840000
0E
#845000
b100 V
1E
#850000
0E
#855000
b101 V
1E
#860000
0E
#865000
b110 V
1E
#870000
0E
#875000
b111 V
1E
#880000
0E
#885000
b1000 V
1E
#890000
0E
#895000
b1001 V
1E
#900000
0E
#905000
b1010 V
1E
#910000
0E
#915000
b1011 V
1E
#920000
0E
#925000
b1100 V
1E
#930000
0E
#935000
b1101 V
1E
#940000
0E
#945000
b1110 V
1E
#950000
0E
#955000
b1111 V
1E
#960000
0E
#965000
b10000 V
1E
#970000
0E
#975000
b10001 V
1E
#980000
0E
#985000
b10010 V
1E
#990000
0E
#995000
b10011 V
1E
#1000000
0E
#1005000
b10100 V
1E
